yaml_validator/__init__.py
yaml_validator/cli.py
yaml_validator/validator.py
yaml_validator-0.3.0.dist-info/licenses/LICENSE
yaml_validator-0.3.0.dist-info/METADATA
yaml_validator-0.3.0.dist-info/WHEEL
yaml_validator-0.3.0.dist-info/entry_points.txt
yaml_validator-0.3.0.dist-info/top_level.txt
yaml_validator-0.3.0.dist-info/RECORD
