Metadata-Version: 2.4
Name: yaml-validator
Version: 0.3.0
Summary: A Python utility for validating user YAML configuration files against a default/template YAML file with support for optional fields
Author-email: Nathan Figueroa <nathan.figueroa@whoi.edu>
Maintainer-email: Nathan Figueroa <nathan.figueroa@whoi.edu>
License-Expression: MIT
Project-URL: Homepage, https://github.com/WHOIGit/example-yaml-validator
Project-URL: Repository, https://github.com/WHOIGit/example-yaml-validator
Project-URL: Issues, https://github.com/WHOIGit/example-yaml-validator/issues
Keywords: yaml,validation,config,configuration
Classifier: Development Status :: 3 - Alpha
Classifier: Intended Audience :: Developers
Classifier: Programming Language :: Python :: 3
Classifier: Programming Language :: Python :: 3.7
Classifier: Programming Language :: Python :: 3.8
Classifier: Programming Language :: Python :: 3.9
Classifier: Programming Language :: Python :: 3.10
Classifier: Programming Language :: Python :: 3.11
Classifier: Programming Language :: Python :: 3.12
Classifier: Programming Language :: Python :: 3.13
Classifier: Topic :: Software Development :: Libraries :: Python Modules
Classifier: Topic :: Utilities
Requires-Python: >=3.7
License-File: LICENSE
Requires-Dist: PyYAML>=6.0.0
Provides-Extra: dev
Requires-Dist: pytest>=7.0.0; extra == "dev"
Dynamic: license-file
